planetboundmass/SWIFT_funcs.py
planetboundmass/__init__.py
planetboundmass/boundmass.py
planetboundmass/gadget_planet_tools.py
planetboundmass/sw_planet_tools.py
planetboundmass/data/s19_forsterite_meltCurve.csv
planetboundmass/data/s19_forsterite_vaporCurve.csv
planetboundmass/data/s19_forsterite_vc.txt
planetboundmass/data/s20_alloy_meltCurve.csv
planetboundmass/data/s20_alloy_vaporCurve.csv
planetboundmass/data/s20_alloy_vc.txt
planetboundmass/data/s20_iron_meltCurve.csv
planetboundmass/data/s20_iron_vaporCurve.csv
planetboundmass/data/s20_iron_vc.txt
planetboundmass-0.1.5.dist-info/LICENSE.txt
planetboundmass-0.1.5.dist-info/METADATA
planetboundmass-0.1.5.dist-info/WHEEL
planetboundmass-0.1.5.dist-info/top_level.txt
planetboundmass-0.1.5.dist-info/RECORD
