Metadata-Version: 2.1
Name: planetboundmass
Version: 0.1.5
Summary: Toolkit to find and analysis bound particles from planetary SWIFTsim simulations
Home-page: https://github.com/JingyaoDOU/planetboundmass
Author: Jingyao Dou
Author-email: Jingyao Dou <jingyao.dou@bristol.ac.uk>
License: MIT License
Project-URL: Homepage, https://github.com/JingyaoDOU/planetboundmass
Classifier: Programming Language :: Python :: 3
Classifier: License :: OSI Approved :: MIT License
Classifier: Operating System :: OS Independent
Requires-Python: <=3.8.18
License-File: LICENSE.txt
Requires-Dist: numpy
Requires-Dist: matplotlib
Requires-Dist: pandas
Requires-Dist: h5py
Requires-Dist: woma
Requires-Dist: unyt
Requires-Dist: swiftsimio
Requires-Dist: scipy
Requires-Dist: seaborn
